{
    "key": "group_60269728c188e",
    "title": "Publications",
    "fields": [
        {
            "key": "field_6026972d5c16d",
            "label": "Δημοσιεύσεις",
            "name": "publications",
            "type": "repeater",
            "instructions": "",
            "required": 0,
            "conditional_logic": 0,
            "wrapper": {
                "width": "",
                "class": "",
                "id": ""
            },
            "collapsed": "",
            "min": 0,
            "max": 0,
            "layout": "row",
            "button_label": "Προσθήκη δημοσίευσης",
            "sub_fields": [
                {
                    "key": "field_602697475c16e",
                    "label": "Έτος",
                    "name": "year",
                    "type": "text",
                    "instructions": "",
                    "required": 0,
                    "conditional_logic": 0,
                    "wrapper": {
                        "width": "",
                        "class": "",
                        "id": ""
                    },
                    "default_value": "",
                    "placeholder": "",
                    "prepend": "",
                    "append": "",
                    "maxlength": ""
                },
                {
                    "key": "field_6026975e5c16f",
                    "label": "Συγγραφείς",
                    "name": "authors",
                    "type": "text",
                    "instructions": "",
                    "required": 0,
                    "conditional_logic": 0,
                    "wrapper": {
                        "width": "",
                        "class": "",
                        "id": ""
                    },
                    "default_value": "",
                    "placeholder": "",
                    "prepend": "",
                    "append": "",
                    "maxlength": ""
                },
                {
                    "key": "field_602697715c170",
                    "label": "Τίτλος",
                    "name": "title",
                    "type": "text",
                    "instructions": "",
                    "required": 0,
                    "conditional_logic": 0,
                    "wrapper": {
                        "width": "",
                        "class": "",
                        "id": ""
                    },
                    "default_value": "",
                    "placeholder": "",
                    "prepend": "",
                    "append": "",
                    "maxlength": ""
                },
                {
                    "key": "field_6026977a5c171",
                    "label": "Περιγραφή",
                    "name": "description",
                    "type": "textarea",
                    "instructions": "",
                    "required": 0,
                    "conditional_logic": 0,
                    "wrapper": {
                        "width": "",
                        "class": "",
                        "id": ""
                    },
                    "default_value": "",
                    "placeholder": "",
                    "maxlength": "",
                    "rows": "",
                    "new_lines": ""
                },
                {
                    "key": "field_6026979b5c172",
                    "label": "PDF",
                    "name": "pdf",
                    "type": "file",
                    "instructions": "",
                    "required": 0,
                    "conditional_logic": 0,
                    "wrapper": {
                        "width": "",
                        "class": "",
                        "id": ""
                    },
                    "return_format": "array",
                    "library": "all",
                    "min_size": "",
                    "max_size": "",
                    "mime_types": ""
                },
                {
                    "key": "field_602697a45c173",
                    "label": "Video",
                    "name": "video",
                    "type": "url",
                    "instructions": "",
                    "required": 0,
                    "conditional_logic": 0,
                    "wrapper": {
                        "width": "",
                        "class": "",
                        "id": ""
                    },
                    "default_value": "",
                    "placeholder": ""
                }
            ]
        }
    ],
    "location": [
        [
            {
                "param": "post_template",
                "operator": "==",
                "value": "page-publications.php"
            }
        ]
    ],
    "menu_order": 0,
    "position": "normal",
    "style": "default",
    "label_placement": "top",
    "instruction_placement": "label",
    "hide_on_screen": "",
    "active": true,
    "description": "",
    "modified": 1613141970
}